[
  {
    "model": "accounts.customuser",
    "pk": 1,
    "fields": {
      "last_login": null,
      "is_superuser": true,
      "username": "admin",
      "first_name": "Admin",
      "last_name": "User",
      "email": "admin@example.com",
      "is_staff": true,
      "is_active": true,
      "date_joined": "2023-01-01T00:00:00Z",
      "groups": [],
      "user_permissions": []
    }
  },
  {
    "model": "accounts.customuser",
    "pk": 2,
    "fields": {
      "last_login": null,
      "is_superuser": false,
      "username": "user1",
      "first_name": "User",
      "last_name": "One",
      "email": "user1@example.com",
      "is_staff": false,
      "is_active": true,
      "date_joined": "2023-01-01T00:00:00Z",
      "groups": [],
      "user_permissions": []
    }
  },
  {
    "model": "accounts.customuser",
    "pk": 3,
    "fields": {
      "last_login": null,
      "is_superuser": false,
      "username": "user2",
      "first_name": "User",
      "last_name": "Two",
      "email": "user2@example.com",
      "is_staff": false,
      "is_active": true,
      "date_joined": "2023-01-01T00:00:00Z",
      "groups": [],
      "user_permissions": []
    }
  },
  {
    "model": "accounts.customuser",
    "pk": 4,
    "fields": {
      "last_login": null,
      "is_superuser": false,
      "username": "user3",
      "first_name": "User",
      "last_name": "Three",
      "email": "user3@example.com",
      "is_staff": false,
      "is_active": true,
      "date_joined": "2023-01-01T00:00:00Z",
      "groups": [],
      "user_permissions": []
    }
  },
  {
    "model": "accounts.customuser",
    "pk": 5,
    "fields": {
      "last_login": null,
      "is_superuser": false,
      "username": "user4",
      "first_name": "User",
      "last_name": "Four",
      "email": "user4@example.com",
      "is_staff": false,
      "is_active": true,
      "date_joined": "2023-01-01T00:00:00Z",
      "groups": [],
      "user_permissions": []
    }
  }
]